LICENSE
MANIFEST.in
README.rst
VERSION
requirements-dev.txt
requirements.txt
setup.cfg
setup.py
heatherr/__init__.py
heatherr/__init__.pyc
heatherr/admin.py
heatherr/admin.pyc
heatherr/apps.py
heatherr/apps.pyc
heatherr/models.py
heatherr/models.pyc
heatherr/settings.py
heatherr/settings.pyc
heatherr/urls.py
heatherr/urls.pyc
heatherr/views.py
heatherr/views.pyc
heatherr/wsgi.py
heatherr.egg-info/PKG-INFO
heatherr.egg-info/SOURCES.txt
heatherr.egg-info/dependency_links.txt
heatherr.egg-info/not-zip-safe
heatherr.egg-info/requires.txt
heatherr.egg-info/top_level.txt
heatherr/account/__init__.py
heatherr/account/__init__.pyc
heatherr/account/urls.py
heatherr/account/urls.pyc
heatherr/account/views.py
heatherr/account/views.pyc
heatherr/account/static/css/bootstrap-theme.css
heatherr/account/static/css/bootstrap-theme.css.map
heatherr/account/static/css/bootstrap-theme.min.css
heatherr/account/static/css/bootstrap-theme.min.css.map
heatherr/account/static/css/bootstrap.css
heatherr/account/static/css/bootstrap.css.map
heatherr/account/static/css/bootstrap.min.css
heatherr/account/static/css/bootstrap.min.css.map
heatherr/account/static/css/frontend.css
heatherr/account/static/css/ie10-viewport-bug-workaround.css
heatherr/account/static/fonts/glyphicons-halflings-regular.eot
heatherr/account/static/fonts/glyphicons-halflings-regular.svg
heatherr/account/static/fonts/glyphicons-halflings-regular.ttf
heatherr/account/static/fonts/glyphicons-halflings-regular.woff
heatherr/account/static/fonts/glyphicons-halflings-regular.woff2
heatherr/account/static/img/bell-small.png
heatherr/account/static/img/bell.png
heatherr/account/static/img/favicon.ico
heatherr/account/static/js/bootstrap.js
heatherr/account/static/js/bootstrap.min.js
heatherr/account/static/js/ie10-viewport-bug-workaround.js
heatherr/account/static/js/npm.js
heatherr/account/templates/base.html
heatherr/account/templates/account/authorize_fail.html
heatherr/account/templates/account/base.html
heatherr/account/templates/account/login.html
heatherr/account/templates/account/new_profile.html
heatherr/account/templates/account/profile.html
heatherr/account/templates/bellman/slackaccount_detail.html
