Metadata-Version: 1.1
Name: heatherr
Version: 1.0.2
Summary: Heatherr
Home-page: http://github.com/smn/heatherr
Author: Praekelt Foundation
Author-email: dev@praekelt.com
License: BSD
Keywords: web
Platform: UNKNOWN
Classifier: Programming Language :: Python
Classifier: Topic :: Internet :: WWW/HTTP
Classifier: Topic :: Internet :: WWW/HTTP :: WSGI :: Application
